mas/__init__.py
mas/mas.py
mas/readme-zh.md
mas/readme.md
mas/account/__init__.py
mas/account/account_manager.py
mas/clinet/__init__.py
mas/clinet/client_post.py
mas/clinet/client_post_real.py
mas/connection/__init__.py
mas/connection/connection.py
mas/docs/images/ai_1.jpg
mas/docs/images/ai_2.jpg
mas/docs/images/ai_3.jpg
mas/docs/images/ai_4.jpg
mas/docs/images/doc.jpg
mas/docs/images/report_1.jpg
mas/docs/images/report_2.jpg
mas/docs/images/report_3.jpg
mas/docs/images/report_4.jpg
mas/docs/images/soft_1.jpg
mas/docs/images/soft_2.jpg
mas/docs/images/soft_3.jpg
mas/docs/licenses/API-LICENSE
mas/enum/__init__.py
mas/enum/env_setting.py
mas/enum/symbol_enum.py
mas/history/__init__.py
mas/history/history_data_manager.py
mas/history/history_data_mt5.py
mas/lang/__init__.py
mas/lang/i18n_strings.py
mas/market_data/__init__.py
mas/market_data/market_data_manager.py
mas/module/__init__.py
mas/module/base.py
mas/module/math_base.py
mas/module/time_helper.py
mas/provider/__init__.py
mas/provider/data_provider.py
mas/receive/__init__.py
mas/receive/receive_manage.py
mas/trade/__init__.py
mas/trade/trade_manager.py
mas/virtual/__init__.py
mas/virtual/virtual_trade.py
mas-0.2.4.dist-info/METADATA
mas-0.2.4.dist-info/WHEEL
mas-0.2.4.dist-info/licenses/LICENSE
mas-0.2.4.dist-info/RECORD
