Metadata-Version: 2.4
Name: mas
Version: 0.2.4
Summary: MAS is a Python library for automated trading and backtesting on MetaTrader 5 with KPI reports and dynamic visualization.
Project-URL: Homepage, https://mindaismart.com/
Project-URL: Register, https://mas.mindaismart.com/
Project-URL: AI Trading Assistant, https://mindaismart.com/product_ai
Project-URL: Documentation, https://doc.mindaismart.com/
Author-email: Sam <mas@mindaismart.com>
License: # LICENSE-API
License-File: LICENSE
Keywords: Algorithmic trading,Automated Trading,Backtesting,Forex,KPI Reports,MT5,MetaTrader5,Quantitative Trading
Classifier: Development Status :: 5 - Production/Stable
Classifier: Intended Audience :: Developers
Classifier: Intended Audience :: Financial and Insurance Industry
Classifier: Intended Audience :: Science/Research
Classifier: License :: Other/Proprietary License
Classifier: Operating System :: OS Independent
Classifier: Programming Language :: Python :: 3.8
Classifier: Programming Language :: Python :: 3.9
Classifier: Programming Language :: Python :: 3.10
Classifier: Programming Language :: Python :: 3.11
Classifier: Topic :: Office/Business :: Financial :: Investment
Requires-Python: >=3.8
Requires-Dist: matplotlib>=3.4.0
Requires-Dist: metatrader5>=5.0.37
Requires-Dist: numpy>=1.21.0
Requires-Dist: pandas>=1.3.0
